mt/__init__.py
mt-0.0.1.dist-info/DESCRIPTION.rst
mt-0.0.1.dist-info/METADATA
mt-0.0.1.dist-info/metadata.json
mt-0.0.1.dist-info/RECORD
mt-0.0.1.dist-info/top_level.txt
mt-0.0.1.dist-info/WHEEL
