Metadata-Version: 1.1
Name: mt
Version: 0.0.1
Summary: marked text data type, Python implementation
Home-page: https://github.com/BlackEarth/mtext
Author: Sean Harrison
Author-email: sah@blackearthgroup.com
License: LGPL 3.0
Platform: UNKNOWN
Classifier: Development Status :: 3 - Alpha
Classifier: Intended Audience :: Developers
Classifier: License :: OSI Approved :: GNU Library or Lesser General Public License (LGPL)
Classifier: Programming Language :: Python :: 3
